feagi_bv_macos/__init__.py
feagi_bv_macos/bin/macos/BrainVisualizer-Remote.app/Contents/Info.plist
feagi_bv_macos/bin/macos/BrainVisualizer-Remote.app/Contents/PkgInfo
feagi_bv_macos/bin/macos/BrainVisualizer-Remote.app/Contents/Frameworks/libfeagi_data_deserializer.dylib
feagi_bv_macos/bin/macos/BrainVisualizer-Remote.app/Contents/Frameworks/libfeagi_shared_video.dylib
feagi_bv_macos/bin/macos/BrainVisualizer-Remote.app/Contents/Frameworks/libfeagi_type_system.dylib
feagi_bv_macos/bin/macos/BrainVisualizer-Remote.app/Contents/MacOS/Brain Visualizer
feagi_bv_macos/bin/macos/BrainVisualizer-Remote.app/Contents/Resources/Brain Visualizer.pck
feagi_bv_macos/bin/macos/BrainVisualizer-Remote.app/Contents/Resources/PrivacyInfo.xcprivacy
feagi_bv_macos/bin/macos/BrainVisualizer-Remote.app/Contents/Resources/icon.icns
feagi_bv_macos/bin/macos/BrainVisualizer-Remote.app/Contents/_CodeSignature/CodeResources
feagi_bv_macos-2.0.3.dist-info/METADATA
feagi_bv_macos-2.0.3.dist-info/WHEEL
feagi_bv_macos-2.0.3.dist-info/top_level.txt
feagi_bv_macos-2.0.3.dist-info/RECORD
