Metadata-Version: 2.4
Name: feagi-bv-macos
Version: 2.0.3
Summary: Brain Visualizer binaries for macOS (part of feagi-bv)
Author-email: "Neuraville Inc." <feagi@neuraville.com>
License: Apache-2.0
Classifier: Development Status :: 4 - Beta
Classifier: Intended Audience :: Developers
Classifier: License :: OSI Approved :: Apache Software License
Classifier: Operating System :: MacOS
Classifier: Programming Language :: Python :: 3
Classifier: Programming Language :: Python :: 3.10
Classifier: Programming Language :: Python :: 3.11
Classifier: Programming Language :: Python :: 3.12
Classifier: Topic :: Scientific/Engineering :: Artificial Intelligence
Requires-Python: >=3.10
